Metadata-Version: 2.2
Name: chemistry-tools
Version: 1.1.1
Summary: Python tools for analysis of chemical compounds.
Author-email: Dominic Davis-Foster <dominic@davis-foster.co.uk>
License: LGPL-3.0-or-later
Keywords: chemistry,utility
Home-page: https://github.com/domdfcoding/chemistry_tools
Project-URL: Issue Tracker, https://github.com/domdfcoding/chemistry_tools/issues
Project-URL: Source Code, https://github.com/domdfcoding/chemistry_tools
Project-URL: Documentation, https://chemistry-tools.readthedocs.io/en/latest
Platform: Windows
Platform: macOS
Platform: Linux
Classifier: Development Status :: 4 - Beta
Classifier: Intended Audience :: Developers
Classifier: Intended Audience :: Education
Classifier: Intended Audience :: Science/Research
Classifier: License :: OSI Approved :: GNU Lesser General Public License v3 or later (LGPLv3+)
Classifier: Operating System :: OS Independent
Classifier: Programming Language :: Python
Classifier: Programming Language :: Python :: 3 :: Only
Classifier: Programming Language :: Python :: 3.8
Classifier: Programming Language :: Python :: 3.9
Classifier: Programming Language :: Python :: 3.10
Classifier: Programming Language :: Python :: 3.11
Classifier: Programming Language :: Python :: 3.12
Classifier: Programming Language :: Python :: Implementation :: CPython
Classifier: Programming Language :: Python :: Implementation :: PyPy
Classifier: Topic :: Database :: Front-Ends
Classifier: Topic :: Scientific/Engineering :: Bio-Informatics
Classifier: Topic :: Scientific/Engineering :: Chemistry
Classifier: Topic :: Software Development :: Libraries :: Python Modules
Classifier: Typing :: Typed
Requires-Python: >=3.8
Requires-Dist: apeye>=0.9.1
Requires-Dist: cachecontrol>=0.13.1
Requires-Dist: domdf-python-tools>=3.6.1
Requires-Dist: enum-tools>=0.10.0
Requires-Dist: filelock>=3.8.0
Requires-Dist: memoized-property>=1.0.3
Requires-Dist: numpy>=1.22
Requires-Dist: pandas>=2.0.0
Requires-Dist: quantities>=0.12.4
Requires-Dist: requests>=2.31.0
Requires-Dist: typing-extensions>=4.1.1
Requires-Dist: cawdrey>=0.5.0; extra == 'pubchem'
Requires-Dist: mathematical>=0.5.1; extra == 'pubchem'
Requires-Dist: pillow>=9.0.0; extra == 'pubchem'
Requires-Dist: pillow<=10.2.0; (platform_python_implementation == "PyPy" and python_version < "3.9" and platform_system == "Windows") and extra == 'pubchem'
Requires-Dist: pyparsing>=2.4.6; extra == 'pubchem'
Requires-Dist: tabulate>=0.8.9; extra == 'pubchem'
Requires-Dist: cawdrey>=0.5.0; extra == 'formulae'
Requires-Dist: mathematical>=0.5.1; extra == 'formulae'
Requires-Dist: pyparsing>=2.4.6; extra == 'formulae'
Requires-Dist: tabulate>=0.8.9; extra == 'formulae'
Requires-Dist: matplotlib>=3.6.0; extra == 'plotting'
Requires-Dist: beautifulsoup4>=4.7.0; extra == 'toxnet'
Requires-Dist: beautifulsoup4>=4.7.0; extra == 'all'
Requires-Dist: cawdrey>=0.5.0; extra == 'all'
Requires-Dist: mathematical>=0.5.1; extra == 'all'
Requires-Dist: matplotlib>=3.6.0; extra == 'all'
Requires-Dist: pillow>=9.0.0; extra == 'all'
Requires-Dist: pillow<=10.2.0; (platform_python_implementation == "PyPy" and python_version < "3.9" and platform_system == "Windows") and extra == 'all'
Requires-Dist: pyparsing>=2.4.6; extra == 'all'
Requires-Dist: tabulate>=0.8.9; extra == 'all'
Provides-Extra: pubchem
Provides-Extra: formulae
Provides-Extra: plotting
Provides-Extra: toxnet
Provides-Extra: all
